hapi/__init__.py
hapi/__main__.py
hapi/conf/__init__.py
hapi/conf/config.py
hapi/utils/__init__.py
hapi/utils/data_utils.py
hapi/utils/mappings_helpers.py
hapi/utils/probabilities_helpers.py
hapi/utils/reader_of_yaml.py
hapi_pyth-0.0.8.dist-info/LICENSE
hapi_pyth-0.0.8.dist-info/METADATA
hapi_pyth-0.0.8.dist-info/WHEEL
hapi_pyth-0.0.8.dist-info/entry_points.txt
hapi_pyth-0.0.8.dist-info/top_level.txt
hapi_pyth-0.0.8.dist-info/RECORD
