Metadata-Version: 2.2
Name: hapi-pyth
Version: 0.0.8
Summary: Haplotype-Aware Probabilistic model for Indels
Home-page: https://github.com/RasmussenLab/HAPI
Classifier: Intended Audience :: Healthcare Industry
Classifier: Intended Audience :: Science/Research
Classifier: License :: OSI Approved :: MIT License
Classifier: Programming Language :: Python :: 3
Classifier: Topic :: Scientific/Engineering :: Bio-Informatics
Requires-Python: >=3.6
License-File: LICENSE
Requires-Dist: numpy
Requires-Dist: pandas
Requires-Dist: pysam
Requires-Dist: PyYAML
